{
  "commentary": "",
  "author": {
    "name": "Lisa Ward",
    "position": "\"If only I had a car, a degree, a spouse, a new home, or a better situation\u2014then I could really serve God!\" Have you ever caught yourself thinking this way? The spirit of discontent can sneak into our lives, whispering that what we have right now just isn\u2019t enough. If only life could shift just a bit, we tell ourselves, then everything would fallinto place. Surely, we can\u2019t be expected to thrive in these current circumstances\u2014they\u2019re just so unreasonable!Paul offers wisdom on this very mindset. His advice, sometimes personal and sometimes divinely inspired, centers on a powerful theme: contentment. Wherever you are\u2014married or single, Jew or Gentile, free or enslaved\u2014God can use you. Your current status isn\u2019t a barrier to serving Him; it\u2019s an opportunity. What matters most is your faithfulness to God in the present, not in some imagined \"better\" future.The key is keeping eternity in focus. Your current situation, however imperfect, is not outside of God\u2019s plan. Instead of waiting for conditions to improve, what might happen if you embraced where you are and trusted God to work through you? Let\u2019s begin living with that confidence, starting today!Clerk for Country Life SDA ChurchCleburne, Texas USA (as of this writing)"
  },
  "pagination": {
    "previous": "bhp/en/bible/1co/6",
    "next": "bhp/en/bible/1co/8",
    "current": "bhp/en/bible/1co/7"
  },
  "date": {
    "original": "December 17, 2024",
    "formatted": "20241217"
  },
  "bible_passage": {
    "verse": "1 Corinthians 7:1-40",
    "chapter": "1 Corinthians 7"
  }
}